[
  {
    "code": "015790",
    "name": "永赢高端装备智选混合发起C"
  },
  {
    "code": "024195",
    "name": "永赢国证商用卫星通信产业ETF发起联接C"
  },
  {
    "code": "015916",
    "name": "永赢医药创新智选混合发起C"
  },
  {
    "code": "024775",
    "name": "永赢上证科创板人工智能指数发起C"
  },
  {
    "code": "018125",
    "name": "永赢先进制造智选混合发起C"
  },
  {
    "code": "025833",
    "name": "天弘中证电网设备主题指数发起C"
  },
  {
    "code": "014087",
    "name": "兴全恒悦180天持有债券C"
  },
  {
    "code": "021173",
    "name": "华安北证50成份指数发起式C"
  },
  {
    "code": "011609",
    "name": "易方达上证科创50联接C"
  },
  {
    "code": "007083",
    "name": "平安高端制造混合C"
  },
  {
    "code": "025167",
    "name": "汇添富恒生港股通中国科技ETF联接C"
  },
  {
    "code": "008280",
    "name": "国泰中证煤炭ETF联接C"
  },
  {
    "code": "012414",
    "name": "招商中证白酒指数(LOF)C"
  },
  {
    "code": "161725",
    "name": "招商中证白酒指数(LOF)A"
  },
  {
    "code": "021087",
    "name": "鹏华国证粮食产业ETF发起式联接C"
  }
]